aipymemtimeprofiler/__init__.py
aipymemtimeprofiler/analyser/__init__.py
aipymemtimeprofiler/analyser/function_extract.py
aipymemtimeprofiler/analyser/performance_analyser.py
aipymemtimeprofiler/config/__init__.py
aipymemtimeprofiler/config/config.py
aipymemtimeprofiler/executable/__init__.py
aipymemtimeprofiler/executable/execute.py
aipymemtimeprofiler/flask_app_profiler/__init__.py
aipymemtimeprofiler/flask_app_profiler/load_flask.py
aipymemtimeprofiler/flask_app_profiler/profiler.py
aipymemtimeprofiler/helpers/__init__.py
aipymemtimeprofiler/helpers/helper.py
aipymemtimeprofiler/profiler/__init__.py
aipymemtimeprofiler/profiler/profile_details.py
aipymemtimeprofiler/vizualization/__init__.py
aipymemtimeprofiler/vizualization/graph.py
aipymemtimeprofiler/vizualization/viz.py
aipymemtimeprofiler-1.1.1.dist-info/METADATA
aipymemtimeprofiler-1.1.1.dist-info/WHEEL
aipymemtimeprofiler-1.1.1.dist-info/entry_points.txt
aipymemtimeprofiler-1.1.1.dist-info/top_level.txt
aipymemtimeprofiler-1.1.1.dist-info/RECORD
